fwipy/__init__.py
fwipy/__version__.py
fwipy/compat.py
fwipy/fwi_base.py
fwipy/player.py
fwipy/readerId.py
fwipy/template.py
fwipy-0.1.4.dist-info/DESCRIPTION.rst
fwipy-0.1.4.dist-info/LICENSE.txt
fwipy-0.1.4.dist-info/METADATA
fwipy-0.1.4.dist-info/RECORD
fwipy-0.1.4.dist-info/WHEEL
fwipy-0.1.4.dist-info/metadata.json
fwipy-0.1.4.dist-info/top_level.txt
