Metadata-Version: 2.0
Name: fwipy
Version: 0.1.4
Summary: Fwipy - Python Wrapper for Content Player Socket Operations
Home-page: https://github.com/fourwindsinteractive/fwipy
Author: Erin O'Connell
Author-email: erin.oconnell@fourwindsinteractive.com
License: Apache 2.0
Platform: UNKNOWN
Classifier: License :: OSI Approved :: MIT License
Classifier: Programming Language :: Python
Classifier: Programming Language :: Python :: 3.6
Classifier: Programming Language :: Python :: Implementation :: CPython
Requires-Python: >=3.6.0
Requires-Dist: requests
